{
  "config": {
    "step": {
      "user": {
        "description": "Enter your PoolCop API key from the PoolCopilot account",
        "data": {
          "api_key": "API Key"
        }
      },
      "flow_rates": {
        "description": "Your pool pump has {pump_speeds} speeds. Configure the flow rates for each speed.\n\nPool volume: {vol} m\u00b3\nDetected flow rate: {flowrate} m\u00b3/h",
        "data": {
          "flow_rate_1": "Flow rate at speed 1 (m\u00b3/h)",
          "flow_rate_2": "Flow rate at speed 2 (m\u00b3/h)",
          "flow_rate_3": "Flow rate at speed 3 (m\u00b3/h)"
        }
      },
      "reauth_confirm": {
        "description": "Your PoolCopilot API key is no longer valid. Please enter a new API key.",
        "data": {
          "api_key": "API Key"
        }
      }
    },
    "abort": {
      "already_configured": "Device is already configured",
      "reauth_successful": "Re-authentication successful"
    },
    "error": {
      "cannot_connect": "Failed to connect",
      "invalid_auth": "Invalid API key",
      "unknown": "Unexpected error"
    }
  },
  "options": {
    "step": {
      "init": {
        "description": "Adjust the flow rate for each pump speed. These values are used to calculate filtration volume.",
        "data": {
          "flow_rate_1": "Flow rate at speed 1 (m\u00b3/h)",
          "flow_rate_2": "Flow rate at speed 2 (m\u00b3/h)",
          "flow_rate_3": "Flow rate at speed 3 (m\u00b3/h)"
        }
      }
    }
  }
}
